{
  "annotations": {
    "list": []
  },
  "editable": true,
  "graphTooltip": 1,
  "id": null,
  "links": [
    {
      "title": "L2 Strategy+Underlying",
      "url": "/d/strategy-pnl-l2",
      "type": "link",
      "targetBlank": false
    },
    {
      "title": "L4 Underlying",
      "url": "/d/strategy-pnl-l4",
      "type": "link",
      "targetBlank": false
    },
    {
      "title": "L5 Portfolio",
      "url": "/d/strategy-pnl-l5",
      "type": "link",
      "targetBlank": false
    }
  ],
  "liveNow": false,
  "refresh": "1m",
  "panels": [
    {
      "datasource": {
        "type": "grafana-clickhouse-datasource",
        "uid": "dfjc5vjyfcc8wf"
      },
      "title": "Aggregate PnL (from backtest day 0) \u2014 Strategy ${strategy_id}",
      "description": "Absolute cumulative PnL (not window-rebased). Shows where the strategy currently stands from its origin.",
      "type": "timeseries",
      "id": 2,
      "gridPos": {
        "x": 0,
        "y": 0,
        "w": 24,
        "h": 8
      },
      "fieldConfig": {
        "defaults": {
          "color": {
            "mode": "palette-classic"
          },
          "custom": {
            "drawStyle": "line",
            "fillOpacity": 10,
            "lineWidth": 2,
            "showPoints": "never",
            "spanNulls": true
          },
          "unit": "percentunit",
          "decimals": 4
        }
      },
      "options": {
        "legend": {
          "calcs": [
            "last",
            "min"
          ],
          "displayMode": "list",
          "placement": "bottom",
          "showLegend": true
        },
        "tooltip": {
          "mode": "multi",
          "sort": "desc"
        }
      },
      "targets": [
        {
          "datasource": {
            "type": "grafana-clickhouse-datasource",
            "uid": "dfjc5vjyfcc8wf"
          },
          "rawSql": "SELECT toStartOfDay(ts) AS time, CASE WHEN '${mode}' = 'raw_weighted' THEN sum(cumulative_pnl * weighting) WHEN '${mode}' = 'equal' THEN avg(cumulative_pnl) ELSE sum(cumulative_pnl * weighting) / nullIf(sum(weighting), 0) END AS `Production PnL` FROM (SELECT * FROM analytics.strategy_pnl_1min_prod_v2 WHERE (${__to} - ${__from}) / 1000 <= 86400 UNION ALL SELECT * FROM analytics.strategy_pnl_1hour_prod_v2 WHERE (${__to} - ${__from}) / 1000 > 86400) FINAL WHERE strategy_table_name LIKE 'sid=${strategy_id}|%' AND ts <= toDateTime(intDiv(${__to},1000)) GROUP BY time ORDER BY time",
          "refId": "A",
          "format": 1,
          "queryType": "sql",
          "meta": {
            "builderOptions": {
              "mode": 0
            }
          }
        },
        {
          "datasource": {
            "type": "grafana-clickhouse-datasource",
            "uid": "dfjc5vjyfcc8wf"
          },
          "rawSql": "SELECT time, `Backtest PnL`, `Benchmark` FROM (SELECT time, `Backtest PnL`, `Benchmark`, n_strats, max(n_strats) OVER (ORDER BY time ROWS BETWEEN 6 PRECEDING AND 1 PRECEDING) AS trailing_max FROM (SELECT toStartOfDay(ts) AS time, CASE WHEN '${mode}' = 'raw_weighted' THEN sum(cumulative_pnl * weighting) WHEN '${mode}' = 'equal' THEN avg(cumulative_pnl) ELSE sum(cumulative_pnl * weighting) / nullIf(sum(weighting), 0) END AS `Backtest PnL`, CASE WHEN '${mode}' = 'raw_weighted' THEN sum(benchmark * weighting) WHEN '${mode}' = 'equal' THEN avg(benchmark) ELSE sum(benchmark * weighting) / nullIf(sum(weighting), 0) END AS `Benchmark`, uniq(strategy_table_name) AS n_strats FROM (SELECT * FROM analytics.strategy_pnl_1min_bt_v2 WHERE (${__to} - ${__from}) / 1000 <= 86400 UNION ALL SELECT * FROM analytics.strategy_pnl_1hour_bt_v2 WHERE (${__to} - ${__from}) / 1000 > 86400) FINAL WHERE strategy_table_name LIKE 'sid=${strategy_id}|%' AND ts <= toDateTime(intDiv(${__to},1000)) GROUP BY time ORDER BY time)) WHERE n_strats >= trailing_max * 0.65 ORDER BY time",
          "refId": "B",
          "format": 1,
          "queryType": "sql",
          "meta": {
            "builderOptions": {
              "mode": 0
            }
          },
          "hide": false
        },
        {
          "datasource": {
            "type": "grafana-clickhouse-datasource",
            "uid": "dfjc5vjyfcc8wf"
          },
          "rawSql": "SELECT toStartOfDay(ts) AS time, CASE WHEN '${mode}' = 'raw_weighted' THEN sum(cumulative_pnl * weighting) WHEN '${mode}' = 'equal' THEN avg(cumulative_pnl) ELSE sum(cumulative_pnl * weighting) / nullIf(sum(weighting), 0) END AS `Real Trade PnL` FROM (SELECT * FROM analytics.strategy_pnl_1min_real_trade_v2 WHERE (${__to} - ${__from}) / 1000 <= 86400 UNION ALL SELECT * FROM analytics.strategy_pnl_1hour_real_trade_v2 WHERE (${__to} - ${__from}) / 1000 > 86400) FINAL WHERE strategy_table_name LIKE 'sid=${strategy_id}|%' AND ts <= toDateTime(intDiv(${__to},1000)) GROUP BY time ORDER BY time",
          "refId": "C",
          "format": 1
        }
      ],
      "hide": true
    },
    {
      "datasource": {
        "type": "grafana-clickhouse-datasource",
        "uid": "dfjc5vjyfcc8wf"
      },
      "title": "Aggregate PnL (from 0%) \u2014 Strategy ${strategy_id}",
      "description": "All instances combined, rebased to 0% at the left edge of the selected time window. Production vs Backtest vs Benchmark.",
      "type": "timeseries",
      "id": 3,
      "gridPos": {
        "x": 0,
        "y": 8,
        "w": 24,
        "h": 8
      },
      "fieldConfig": {
        "defaults": {
          "color": {
            "mode": "palette-classic"
          },
          "custom": {
            "drawStyle": "line",
            "fillOpacity": 10,
            "lineWidth": 3,
            "showPoints": "never",
            "spanNulls": true
          },
          "unit": "percentunit",
          "decimals": 4
        }
      },
      "options": {
        "legend": {
          "calcs": [
            "last",
            "min"
          ],
          "displayMode": "list",
          "placement": "bottom",
          "showLegend": true
        },
        "tooltip": {
          "mode": "multi",
          "sort": "desc"
        }
      },
      "targets": [
        {
          "datasource": {
            "type": "grafana-clickhouse-datasource",
            "uid": "dfjc5vjyfcc8wf"
          },
          "rawSql": "SELECT toStartOfMinute(ts) AS time, CASE WHEN '${mode}' = 'raw_weighted' THEN sum(p * weighting) WHEN '${mode}' = 'equal' THEN avg(p) ELSE sum(p * weighting) / nullIf(sum(weighting), 0) END AS `Production PnL` FROM (SELECT ts, strategy_table_name, weighting, cumulative_pnl - first_value(cumulative_pnl) OVER (PARTITION BY strategy_table_name ORDER BY ts) AS p FROM (SELECT * FROM analytics.strategy_pnl_1min_prod_v2 WHERE (${__to} - ${__from}) / 1000 <= 86400 UNION ALL SELECT * FROM analytics.strategy_pnl_1hour_prod_v2 WHERE (${__to} - ${__from}) / 1000 > 86400) FINAL WHERE strategy_table_name LIKE 'sid=${strategy_id}|%' AND ts >= toDateTime(intDiv(${__from},1000)) AND ts <= toDateTime(intDiv(${__to},1000))) GROUP BY time ORDER BY time",
          "refId": "A",
          "format": 1,
          "queryType": "sql",
          "meta": {
            "builderOptions": {
              "mode": 0
            }
          }
        },
        {
          "datasource": {
            "type": "grafana-clickhouse-datasource",
            "uid": "dfjc5vjyfcc8wf"
          },
          "rawSql": "SELECT time, `Backtest PnL`, `Benchmark` FROM (SELECT time, `Backtest PnL`, `Benchmark`, n_strats, max(n_strats) OVER (ORDER BY time ROWS BETWEEN 30 PRECEDING AND 1 PRECEDING) AS trailing_max FROM (SELECT toStartOfMinute(ts) AS time, CASE WHEN '${mode}' = 'raw_weighted' THEN sum(p * weighting) WHEN '${mode}' = 'equal' THEN avg(p) ELSE sum(p * weighting) / nullIf(sum(weighting), 0) END AS `Backtest PnL`, CASE WHEN '${mode}' = 'raw_weighted' THEN sum(b * weighting) WHEN '${mode}' = 'equal' THEN avg(b) ELSE sum(b * weighting) / nullIf(sum(weighting), 0) END AS `Benchmark`, uniq(strategy_table_name) AS n_strats FROM (SELECT ts, strategy_table_name, weighting, cumulative_pnl - first_value(cumulative_pnl) OVER (PARTITION BY strategy_table_name ORDER BY ts) AS p, benchmark - first_value(benchmark) OVER (PARTITION BY strategy_table_name ORDER BY ts) AS b FROM (SELECT * FROM analytics.strategy_pnl_1min_bt_v2 WHERE (${__to} - ${__from}) / 1000 <= 86400 UNION ALL SELECT * FROM analytics.strategy_pnl_1hour_bt_v2 WHERE (${__to} - ${__from}) / 1000 > 86400) FINAL WHERE strategy_table_name LIKE 'sid=${strategy_id}|%' AND ts >= toDateTime(intDiv(${__from},1000)) AND ts <= toDateTime(intDiv(${__to},1000))) AS t GROUP BY time ORDER BY time)) WHERE n_strats >= trailing_max * 0.65 ORDER BY time",
          "refId": "B",
          "format": 1,
          "queryType": "sql",
          "meta": {
            "builderOptions": {
              "mode": 0
            }
          },
          "hide": false
        },
        {
          "datasource": {
            "type": "grafana-clickhouse-datasource",
            "uid": "dfjc5vjyfcc8wf"
          },
          "rawSql": "SELECT toStartOfMinute(ts) AS time, CASE WHEN '${mode}' = 'raw_weighted' THEN sum(p * weighting) WHEN '${mode}' = 'equal' THEN avg(p) ELSE sum(p * weighting) / nullIf(sum(weighting), 0) END AS `Real Trade PnL` FROM (SELECT ts, strategy_table_name, weighting, cumulative_pnl - first_value(cumulative_pnl) OVER (PARTITION BY strategy_table_name ORDER BY ts) AS p FROM (SELECT * FROM analytics.strategy_pnl_1min_real_trade_v2 WHERE (${__to} - ${__from}) / 1000 <= 86400 UNION ALL SELECT * FROM analytics.strategy_pnl_1hour_real_trade_v2 WHERE (${__to} - ${__from}) / 1000 > 86400) FINAL WHERE strategy_table_name LIKE 'sid=${strategy_id}|%' AND ts >= toDateTime(intDiv(${__from},1000)) AND ts <= toDateTime(intDiv(${__to},1000))) GROUP BY time ORDER BY time",
          "refId": "C",
          "format": 1
        }
      ],
      "hide": true
    },
    {
      "datasource": {
        "type": "grafana-clickhouse-datasource",
        "uid": "dfjc5vjyfcc8wf"
      },
      "title": "Aggregate Drawdown",
      "type": "timeseries",
      "id": 4,
      "gridPos": {
        "x": 0,
        "y": 16,
        "w": 24,
        "h": 7
      },
      "fieldConfig": {
        "defaults": {
          "color": {
            "mode": "palette-classic"
          },
          "custom": {
            "drawStyle": "line",
            "fillOpacity": 10,
            "lineWidth": 2,
            "showPoints": "never",
            "spanNulls": true
          },
          "unit": "percentunit"
        }
      },
      "options": {
        "legend": {
          "calcs": [
            "min"
          ],
          "displayMode": "list",
          "placement": "bottom",
          "showLegend": true
        },
        "tooltip": {
          "mode": "multi",
          "sort": "asc"
        }
      },
      "targets": [
        {
          "datasource": {
            "type": "grafana-clickhouse-datasource",
            "uid": "dfjc5vjyfcc8wf"
          },
          "rawSql": "SELECT time, agg_pnl - max(agg_pnl) OVER (ORDER BY time ROWS BETWEEN UNBOUNDED PRECEDING AND CURRENT ROW) AS `Production Drawdown` FROM (SELECT toStartOfMinute(ts) AS time, CASE WHEN '${mode}' = 'raw_weighted' THEN sum(p * weighting) WHEN '${mode}' = 'equal' THEN avg(p) ELSE sum(p * weighting) / nullIf(sum(weighting), 0) END AS agg_pnl FROM (SELECT ts, strategy_table_name, weighting, cumulative_pnl - first_value(cumulative_pnl) OVER (PARTITION BY strategy_table_name ORDER BY ts) AS p FROM (SELECT * FROM analytics.strategy_pnl_1min_prod_v2 WHERE (${__to} - ${__from}) / 1000 <= 86400 UNION ALL SELECT * FROM analytics.strategy_pnl_1hour_prod_v2 WHERE (${__to} - ${__from}) / 1000 > 86400) FINAL WHERE (empty('${strategy_id}') OR strategy_id = ${strategy_id}) AND ts >= toDateTime(intDiv(${__from},1000)) AND ts <= toDateTime(intDiv(${__to},1000))) GROUP BY time) ORDER BY time",
          "refId": "A",
          "format": 1,
          "queryType": "sql",
          "meta": {
            "builderOptions": {
              "mode": 0
            }
          }
        },
        {
          "datasource": {
            "type": "grafana-clickhouse-datasource",
            "uid": "dfjc5vjyfcc8wf"
          },
          "rawSql": "SELECT time, agg_pnl - max(agg_pnl) OVER (ORDER BY time ROWS BETWEEN UNBOUNDED PRECEDING AND CURRENT ROW) AS `Backtest Drawdown` FROM (SELECT time, agg_pnl FROM (SELECT time, agg_pnl, n_strats, max(n_strats) OVER (ORDER BY time ROWS BETWEEN 30 PRECEDING AND 1 PRECEDING) AS trailing_max FROM (SELECT toStartOfMinute(ts) AS time, CASE WHEN '${mode}' = 'raw_weighted' THEN sum(p * weighting) WHEN '${mode}' = 'equal' THEN avg(p) ELSE sum(p * weighting) / nullIf(sum(weighting), 0) END AS agg_pnl, uniq(strategy_table_name) AS n_strats FROM (SELECT ts, strategy_table_name, weighting, cumulative_pnl - first_value(cumulative_pnl) OVER (PARTITION BY strategy_table_name ORDER BY ts) AS p FROM (SELECT * FROM analytics.strategy_pnl_1min_bt_v2 WHERE (${__to} - ${__from}) / 1000 <= 86400 UNION ALL SELECT * FROM analytics.strategy_pnl_1hour_bt_v2 WHERE (${__to} - ${__from}) / 1000 > 86400) FINAL WHERE (empty('${strategy_id}') OR strategy_id = ${strategy_id}) AND ts >= toDateTime(intDiv(${__from},1000)) AND ts <= toDateTime(intDiv(${__to},1000))) AS t GROUP BY time ORDER BY time)) WHERE n_strats >= trailing_max * 0.65) ORDER BY time",
          "refId": "B",
          "format": 1,
          "queryType": "sql",
          "meta": {
            "builderOptions": {
              "mode": 0
            }
          },
          "hide": false
        },
        {
          "datasource": {
            "type": "grafana-clickhouse-datasource",
            "uid": "dfjc5vjyfcc8wf"
          },
          "rawSql": "SELECT time, agg_bm - max(agg_bm) OVER (ORDER BY time ROWS BETWEEN UNBOUNDED PRECEDING AND CURRENT ROW) AS `Benchmark Drawdown` FROM (SELECT toStartOfMinute(ts) AS time, CASE WHEN '${mode}' = 'raw_weighted' THEN sum(b * weighting) WHEN '${mode}' = 'equal' THEN avg(b) ELSE sum(b * weighting) / nullIf(sum(weighting), 0) END AS agg_bm FROM (SELECT ts, strategy_table_name, weighting, benchmark - first_value(benchmark) OVER (PARTITION BY strategy_table_name ORDER BY ts) AS b FROM (SELECT * FROM analytics.strategy_pnl_1min_prod_v2 WHERE (${__to} - ${__from}) / 1000 <= 86400 UNION ALL SELECT * FROM analytics.strategy_pnl_1hour_prod_v2 WHERE (${__to} - ${__from}) / 1000 > 86400) FINAL WHERE (empty('${strategy_id}') OR strategy_id = ${strategy_id}) AND ts >= toDateTime(intDiv(${__from},1000)) AND ts <= toDateTime(intDiv(${__to},1000))) GROUP BY time) ORDER BY time",
          "refId": "C",
          "format": 1,
          "queryType": "sql",
          "meta": {
            "builderOptions": {
              "mode": 0
            }
          },
          "hide": false
        },
        {
          "datasource": {
            "type": "grafana-clickhouse-datasource",
            "uid": "dfjc5vjyfcc8wf"
          },
          "rawSql": "SELECT time, agg_pnl - max(agg_pnl) OVER (ORDER BY time ROWS BETWEEN UNBOUNDED PRECEDING AND CURRENT ROW) AS `Real Trade Drawdown` FROM (SELECT toStartOfMinute(ts) AS time, CASE WHEN '${mode}' = 'raw_weighted' THEN sum(p * weighting) WHEN '${mode}' = 'equal' THEN avg(p) ELSE sum(p * weighting) / nullIf(sum(weighting), 0) END AS agg_pnl FROM (SELECT ts, strategy_table_name, weighting, cumulative_pnl - first_value(cumulative_pnl) OVER (PARTITION BY strategy_table_name ORDER BY ts) AS p FROM (SELECT * FROM analytics.strategy_pnl_1min_real_trade_v2 WHERE (${__to} - ${__from}) / 1000 <= 86400 UNION ALL SELECT * FROM analytics.strategy_pnl_1hour_real_trade_v2 WHERE (${__to} - ${__from}) / 1000 > 86400) FINAL WHERE (empty('${strategy_id}') OR strategy_id = ${strategy_id}) AND ts >= toDateTime(intDiv(${__from},1000)) AND ts <= toDateTime(intDiv(${__to},1000))) GROUP BY time) ORDER BY time",
          "refId": "D",
          "format": 1,
          "queryType": "sql",
          "meta": {
            "builderOptions": {
              "mode": 0
            }
          }
        }
      ],
      "hide": true
    },
    {
      "datasource": {
        "type": "grafana-clickhouse-datasource",
        "uid": "dfjc5vjyfcc8wf"
      },
      "title": "Aggregate Position \u2014 Strategy ${strategy_id}",
      "description": "Aggregated position across all instances of this strategy. Aggregation follows the selected PnL mode (rescaled/raw weighted/equal weighted).",
      "type": "timeseries",
      "id": 5,
      "gridPos": {
        "x": 0,
        "y": 23,
        "w": 24,
        "h": 6
      },
      "fieldConfig": {
        "defaults": {
          "color": {
            "mode": "palette-classic"
          },
          "custom": {
            "drawStyle": "line",
            "fillOpacity": 5,
            "lineWidth": 1,
            "showPoints": "never",
            "spanNulls": true
          },
          "unit": "short",
          "decimals": 6
        }
      },
      "options": {
        "legend": {
          "displayMode": "list",
          "placement": "bottom",
          "showLegend": true
        },
        "tooltip": {
          "mode": "multi",
          "sort": "desc"
        }
      },
      "targets": [
        {
          "datasource": {
            "type": "grafana-clickhouse-datasource",
            "uid": "dfjc5vjyfcc8wf"
          },
          "rawSql": "SELECT $__timeInterval(ts) AS time, CASE WHEN '${mode}' = 'raw_weighted' THEN sum(position * weighting) WHEN '${mode}' = 'equal' THEN avg(position) ELSE sum(position * weighting) / nullIf(sum(weighting), 0) END AS `Production Position` FROM (SELECT * FROM analytics.strategy_pnl_1min_prod_v2 WHERE (${__to} - ${__from}) / 1000 <= 86400 UNION ALL SELECT * FROM analytics.strategy_pnl_1hour_prod_v2 WHERE (${__to} - ${__from}) / 1000 > 86400) FINAL WHERE strategy_table_name LIKE 'sid=${strategy_id}|%' AND ts >= toDateTime(intDiv(${__from},1000)) AND ts <= toDateTime(intDiv(${__to},1000)) GROUP BY time ORDER BY time",
          "refId": "A",
          "format": 1,
          "queryType": "sql",
          "meta": {
            "builderOptions": {
              "mode": 0
            }
          }
        },
        {
          "datasource": {
            "type": "grafana-clickhouse-datasource",
            "uid": "dfjc5vjyfcc8wf"
          },
          "rawSql": "SELECT time, `Backtest Position` FROM (SELECT time, `Backtest Position`, n_strats, max(n_strats) OVER (ORDER BY time ROWS BETWEEN 6 PRECEDING AND 1 PRECEDING) AS trailing_max FROM (SELECT $__timeInterval(ts) AS time, CASE WHEN '${mode}' = 'raw_weighted' THEN sum(position * weighting) WHEN '${mode}' = 'equal' THEN avg(position) ELSE sum(position * weighting) / nullIf(sum(weighting), 0) END AS `Backtest Position`, uniq(strategy_table_name) AS n_strats FROM (SELECT * FROM analytics.strategy_pnl_1min_bt_v2 WHERE (${__to} - ${__from}) / 1000 <= 86400 UNION ALL SELECT * FROM analytics.strategy_pnl_1hour_bt_v2 WHERE (${__to} - ${__from}) / 1000 > 86400) FINAL WHERE strategy_table_name LIKE 'sid=${strategy_id}|%' AND ts >= toDateTime(intDiv(${__from},1000)) AND ts <= toDateTime(intDiv(${__to},1000)) GROUP BY time ORDER BY time)) WHERE n_strats >= trailing_max * 0.65 ORDER BY time",
          "refId": "B",
          "format": 1,
          "queryType": "sql",
          "meta": {
            "builderOptions": {
              "mode": 0
            }
          }
        },
        {
          "datasource": {
            "type": "grafana-clickhouse-datasource",
            "uid": "dfjc5vjyfcc8wf"
          },
          "rawSql": "SELECT $__timeInterval(ts) AS time, CASE WHEN '${mode}' = 'raw_weighted' THEN sum(position * weighting) WHEN '${mode}' = 'equal' THEN avg(position) ELSE sum(position * weighting) / nullIf(sum(weighting), 0) END AS `Real Trade Position` FROM (SELECT * FROM analytics.strategy_pnl_1min_real_trade_v2 WHERE (${__to} - ${__from}) / 1000 <= 86400 UNION ALL SELECT * FROM analytics.strategy_pnl_1hour_real_trade_v2 WHERE (${__to} - ${__from}) / 1000 > 86400) FINAL WHERE strategy_table_name LIKE 'sid=${strategy_id}|%' AND ts >= toDateTime(intDiv(${__from},1000)) AND ts <= toDateTime(intDiv(${__to},1000)) GROUP BY time ORDER BY time",
          "refId": "C",
          "format": 1,
          "queryType": "sql",
          "meta": {
            "builderOptions": {
              "mode": 0
            }
          }
        }
      ],
      "hide": true
    },
    {
      "datasource": {
        "type": "grafana-clickhouse-datasource",
        "uid": "dfjc5vjyfcc8wf"
      },
      "title": "Per-Instance Position \u2014 Strategy ${strategy_id}",
      "description": "Individual position for each instance within this strategy. Each line is one strategy_table_name.",
      "type": "timeseries",
      "id": 6,
      "gridPos": {
        "x": 0,
        "y": 29,
        "w": 24,
        "h": 6
      },
      "fieldConfig": {
        "defaults": {
          "color": {
            "mode": "palette-classic"
          },
          "custom": {
            "drawStyle": "line",
            "fillOpacity": 0,
            "lineWidth": 1,
            "showPoints": "never",
            "spanNulls": true
          },
          "unit": "short",
          "decimals": 6
        }
      },
      "options": {
        "legend": {
          "calcs": [
            "last"
          ],
          "displayMode": "table",
          "placement": "right",
          "showLegend": true
        },
        "tooltip": {
          "mode": "multi",
          "sort": "desc"
        }
      },
      "transformations": [
        {
          "id": "partitionByValues",
          "options": {
            "fields": [
              "strategy_table_name"
            ],
            "keepFields": false
          }
        }
      ],
      "targets": [
        {
          "datasource": {
            "type": "grafana-clickhouse-datasource",
            "uid": "dfjc5vjyfcc8wf"
          },
          "rawSql": "SELECT toStartOfFiveMinutes(ts) AS time, strategy_table_name, argMax(position, ts) AS position FROM (SELECT * FROM analytics.strategy_pnl_1min_prod_v2 WHERE (${__to} - ${__from}) / 1000 <= 86400 UNION ALL SELECT * FROM analytics.strategy_pnl_1hour_prod_v2 WHERE (${__to} - ${__from}) / 1000 > 86400) FINAL WHERE strategy_table_name LIKE 'sid=${strategy_id}|%' AND ts >= toDateTime(intDiv(${__from},1000)) AND ts <= toDateTime(intDiv(${__to},1000)) GROUP BY time, strategy_table_name ORDER BY time",
          "refId": "A",
          "format": 0,
          "queryType": "sql",
          "meta": {
            "builderOptions": {
              "mode": 0
            }
          }
        }
      ]
    }
  ],
  "templating": {
    "list": [
      {
        "name": "strategy_id",
        "label": "Strategy ID",
        "type": "query",
        "datasource": {
          "type": "grafana-clickhouse-datasource",
          "uid": "dfjc5vjyfcc8wf"
        },
        "definition": "SELECT DISTINCT toString(strategy_id) FROM analytics.strategy_output_history_v2 ORDER BY strategy_id",
        "query": "SELECT DISTINCT toString(strategy_id) FROM analytics.strategy_output_history_v2 ORDER BY strategy_id",
        "refresh": 1,
        "sort": 1,
        "multi": false,
        "includeAll": false
      },
      {
        "name": "mode",
        "label": "PnL Mode",
        "type": "custom",
        "query": "Rescaled : rescaled,Raw Weighted : raw_weighted,Equal Weighted : equal",
        "current": {
          "text": "Rescaled",
          "value": "rescaled"
        },
        "options": [
          {
            "text": "Rescaled",
            "value": "rescaled",
            "selected": true
          },
          {
            "text": "Raw Weighted",
            "value": "raw_weighted",
            "selected": false
          },
          {
            "text": "Equal Weighted",
            "value": "equal",
            "selected": false
          }
        ],
        "hide": 0,
        "multi": false,
        "includeAll": false,
        "description": "Rescaled: sum(pnl*w)/sum(w) \u2014 normalized to 100%. Raw Weighted: sum(pnl*w) \u2014 actual portfolio contribution. Equal Weighted: avg(pnl) \u2014 every instance equal."
      }
    ]
  },
  "time": {
    "from": "now-7d",
    "to": "now"
  },
  "timezone": "utc",
  "title": "Strategy PnL \u2014 L3 Strategy ID",
  "uid": "strategy-pnl-l3",
  "version": 21
}